ledsc/__init__.py
ledsc/ledsc.py
ledsc-1.0.6.dist-info/METADATA
ledsc-1.0.6.dist-info/WHEEL
ledsc-1.0.6.dist-info/top_level.txt
ledsc-1.0.6.dist-info/RECORD
