Metadata-Version: 2.1
Name: ledsc
Version: 1.0.6
Summary: Library for communicate with led string controller
Author-email: Patrik Kratochvil <info@ledsc.eu>
Classifier: Programming Language :: Python :: 3
Classifier: License :: OSI Approved :: MIT License
Classifier: Operating System :: OS Independent
Requires-Python: >=3.8
Requires-Dist: pymodbus ~=3.5.4
Requires-Dist: pyserial ~=3.5
